{
    "name": "Kinshi Knight",
    "description": "A flying knight who controls the skies",
    "type": ["Flying"],
    "tier": "Advanced",
    "requires": "All (Bows C+) (Required (Flying C+)) (Required (Level 15))",
    "abilities": ["Bow Advantage", "Air Superiority", "Canto"],
    "arts": [],
    "growths": {
        "hp": 20,
        "str": 15,
        "mag": 15,
        "dex": 25,
        "spd": 30,
        "def": 10,
        "res": 10,
        "lck": 15
      },
    "modifiers": {
        "hp": 4,
        "str": 1,
        "mag": 0,
        "dex": 5,
        "spd": 4,
        "def": 2,
        "res": 2,
        "lck": 4,
        "mov": 5
    },
    "mount": {
        "hp": 0,
        "str": 1,
        "mag": 0,
        "dex": 0,
        "spd": 2,
        "def": 0,
        "res": 0,
        "lck": 0,
        "mov": 2
    },

    "default_base": "Archer",
    "default_preset": "Speed/Resistance/Luck",
    "default_mainarm": "Bows",
    "default_sidearm": "Lances",
    "comment": "Items in growth, modifiers, and mount should be integers",
    "tags": [],
    "hidden": false
}