{
  "name": "Poltergeist",
  "description": "A spirit of mischief.",
  "type": ["Flying", "Monster"],
  "tier": "Phantom",
  "requires": "Innate",
  "abilities": ["Pass"],
  "arts": [],
  "growths": {
    "hp": 0,
    "str": 25,
    "mag": 25,
    "dex": 45,
    "spd": 60,
    "def": 0,
    "res": 0,
    "lck": 40
  },
  "modifiers": {
    "hp": 1,
    "str": 5,
    "mag": 5,
    "dex": 10,
    "spd": 18,
    "def": 0,
    "res": 0,
    "lck": 6,
    "mov": 4
  },
  "mount": 0,

  "default_base": "Poltergeist",
  "default_preset": "Custom",
  "default_mainarm": "Poltergeist",
  "default_sidearm": "None",
  "comment": "Items in growth, modifiers, and mount should be integers",
  "tags": [],
  "hidden": false
}